funasr_onnx/__init__.py
funasr_onnx/paraformer_bin.py
funasr_onnx/paraformer_online_bin.py
funasr_onnx/punc_bin.py
funasr_onnx/sensevoice_bin.py
funasr_onnx/vad_bin.py
funasr_onnx/utils/__init__.py
funasr_onnx/utils/e2e_vad.py
funasr_onnx/utils/frontend.py
funasr_onnx/utils/postprocess_utils.py
funasr_onnx/utils/sentencepiece_tokenizer.py
funasr_onnx/utils/timestamp_utils.py
funasr_onnx/utils/utils.py
funasr_onnx-0.4.1.dist-info/METADATA
funasr_onnx-0.4.1.dist-info/WHEEL
funasr_onnx-0.4.1.dist-info/top_level.txt
funasr_onnx-0.4.1.dist-info/RECORD
