Metadata-Version: 2.1
Name: funasr-onnx
Version: 0.4.1
Summary: FunASR: A Fundamental End-to-End Speech Recognition Toolkit
Home-page: https://github.com/alibaba-damo-academy/FunASR.git
Author: Speech Lab of DAMO Academy, Alibaba Group
Author-email: funasr@list.alibaba-inc.com
License: MIT
Keywords: funasr,asr
Platform: Any
Classifier: Programming Language :: Python :: 3.6
Classifier: Programming Language :: Python :: 3.7
Classifier: Programming Language :: Python :: 3.8
Classifier: Programming Language :: Python :: 3.9
Classifier: Programming Language :: Python :: 3.10
Requires-Dist: librosa
Requires-Dist: onnxruntime (>=1.7.0)
Requires-Dist: scipy
Requires-Dist: numpy (<=1.26.4)
Requires-Dist: kaldi-native-fbank
Requires-Dist: PyYAML (>=5.1.2)
Requires-Dist: onnx
Requires-Dist: sentencepiece
